{"rustc":4758242423518056681,"features":"[\"default\", \"perf\", \"perf-backtrack\", \"perf-cache\", \"perf-dfa\", \"perf-inline\", \"perf-literal\", \"perf-onepass\", \"std\", \"unicode\", \"unicode-age\", \"unicode-bool\", \"unicode-case\", \"unicode-gencat\", \"unicode-perl\", \"unicode-script\", \"unicode-segment\"]","declared_features":"[\"default\", \"logging\", \"pattern\", \"perf\", \"perf-backtrack\", \"perf-cache\", \"perf-dfa\", \"perf-dfa-full\", \"perf-inline\", \"perf-literal\", \"perf-onepass\", \"std\", \"unicode\", \"unicode-age\", \"unicode-bool\", \"unicode-case\", \"unicode-gencat\", \"unicode-perl\", \"unicode-script\", \"unicode-segment\", \"unstable\", \"use_std\"]","target":5796931310894148030,"profile":2040997289075261528,"path":15773657595669158494,"deps":[[555019317135488525,"regex_automata",false,4029883591835695275],[2779309023524819297,"aho_corasick",false,5186054881011408634],[3129130049864710036,"memchr",false,11912253457097117564],[9408802513701742484,"regex_syntax",false,379357441199252884]],"local":[{"CheckDepInfo":{"dep_info":"release/.fingerprint/regex-7b1959992e53a08b/dep-lib-regex","checksum":false}}],"rustflags":[],"config":2069994364910194474,"compile_kind":0}